juicebox_notebook/__init__.py
juicebox_notebook/browser.py
juicebox_notebook/file_reader.py
juicebox_notebook/js/juicebox.min.js
juicebox_notebook/js/localNotebookFile.js
juicebox_notebook/js/messageHandler.js
juicebox_notebook-0.2.1.dist-info/LICENSE.md
juicebox_notebook-0.2.1.dist-info/METADATA
juicebox_notebook-0.2.1.dist-info/WHEEL
juicebox_notebook-0.2.1.dist-info/top_level.txt
juicebox_notebook-0.2.1.dist-info/RECORD
