Metadata-Version: 2.1
Name: juicebox-notebook
Version: 0.2.1
Summary: Package for embedding the juicebox.js hic visualization in IPython notebooks
Home-page: https://github.com/igvteam/juicebox-notebook
Author: Jim Robinson
License: MIT
Keywords: juicebox,bioinformatics,genomics,visualization,ipython,jupyter,colab
Platform: UNKNOWN
Classifier: Development Status :: 4 - Beta
Classifier: Intended Audience :: Science/Research
Classifier: Intended Audience :: Developers
Classifier: License :: OSI Approved :: MIT License
Classifier: Programming Language :: Python
Classifier: Framework :: IPython
License-File: LICENSE.md
